rubix/__init__.py
rubix/client.py
rubix/did.py
rubix/querier.py
rubix/signer.py
rubix/crypto/account.py
rubix/crypto/bip39.py
rubix/crypto/pem.py
rubix/crypto/secp256k1.py
rubix/models/querier.py
rubix/models/result.py
rubix/utils/validate.py
rubix_py-0.4.0.dist-info/licenses/LICENSE
rubix_py-0.4.0.dist-info/METADATA
rubix_py-0.4.0.dist-info/WHEEL
rubix_py-0.4.0.dist-info/top_level.txt
rubix_py-0.4.0.dist-info/RECORD
