Metadata-Version: 2.4
Name: rubix-py
Version: 0.4.0
Summary: Rubix Client SDK for Python
Author-email: Arnab Ghose <arnab.g@rubix.net>
Maintainer-email: Arnab Ghose <arnab.g@rubix.net>
License: MIT
Project-URL: Homepage, https://github.com/rubixchain/rubix-sdk-py
Project-URL: Repository, https://github.com/rubixchain/rubix-sdk-py
Project-URL: Bug Tracker, https://github.com/rubixchain/rubix-sdk-py/issues
Keywords: blockchain,web3,sdk,cryptography,nft
Requires-Python: >=3.10
License-File: LICENSE
Requires-Dist: requests>=2.31.0
Requires-Dist: ecdsa>=0.19.1
Requires-Dist: bip32utils>=0.3.post4
Requires-Dist: mnemonic>=0.21
Requires-Dist: ECPy>=1.2.5
Requires-Dist: py-cid>=0.3.1
Requires-Dist: coincurve>=21.0.0
Requires-Dist: cryptography>=45.0.7
Dynamic: license-file
